scrapesage/__init__.py
scrapesage/core.py
scrapesage/scraper.py
scrapesage-1.0.0.dist-info/licenses/LICENSE
scrapesage-1.0.0.dist-info/METADATA
scrapesage-1.0.0.dist-info/WHEEL
scrapesage-1.0.0.dist-info/top_level.txt
scrapesage-1.0.0.dist-info/RECORD
