Metadata-Version: 2.4
Name: ScrapeSage
Version: 1.0.0
Summary: A comprehensive web scraping and summarization library using multiple search engines and AI
Author-email: ScrapeSage <contact@scrapesage.com>
License: MIT
Project-URL: Homepage, https://github.com/akillabs/scrapesage
Project-URL: Documentation, https://github.com/akillabs/scrapesage#readme
Project-URL: Repository, https://github.com/akillabs/scrapesage.git
Project-URL: Bug Tracker, https://github.com/akillabs/scrapesage/issues
Keywords: scraping,web scraping,ai,summarization,search,playwright,gemini
Classifier: Development Status :: 4 - Beta
Classifier: Intended Audience :: Developers
Classifier: License :: OSI Approved :: MIT License
Classifier: Operating System :: OS Independent
Classifier: Programming Language :: Python :: 3
Classifier: Programming Language :: Python :: 3.8
Classifier: Programming Language :: Python :: 3.9
Classifier: Programming Language :: Python :: 3.10
Classifier: Programming Language :: Python :: 3.11
Classifier: Programming Language :: Python :: 3.12
Classifier: Topic :: Internet :: WWW/HTTP :: Indexing/Search
Classifier: Topic :: Software Development :: Libraries :: Python Modules
Classifier: Topic :: Text Processing :: General
Requires-Python: >=3.8
License-File: LICENSE
Requires-Dist: requests>=2.25.0
Requires-Dist: duckduckgo-search>=4.0.0
Requires-Dist: playwright>=1.30.0
Requires-Dist: google-generativeai>=0.3.0
Requires-Dist: beautifulsoup4>=4.9.0
Requires-Dist: tenacity>=8.0.0
Provides-Extra: dev
Requires-Dist: pytest>=6.0; extra == "dev"
Requires-Dist: pytest-cov>=2.0; extra == "dev"
Requires-Dist: black>=21.0; extra == "dev"
Requires-Dist: flake8>=3.8; extra == "dev"
Requires-Dist: mypy>=0.800; extra == "dev"
Requires-Dist: build>=0.8.0; extra == "dev"
Requires-Dist: twine>=4.0.0; extra == "dev"
Dynamic: license-file
